{
  "name": "Environment",
  "tree": {
    "$className": "Folder",
    "Baseplate": {
      "$className": "Part",
      "$properties": {
        "Anchored": true,
      "Color": [
        0.38823,
        0.37254,
        0.38823
      ],
      "Locked": true,
      "Position": [
        0,
        -10,
        0
      ],
      "Size": [
        512,
        20,
        512
      ]
    }
  },
  "SpawnLocation": {
    "$className": "SpawnLocation",
    "$properties": {
      "Anchored": true,
      "Position": [
        0,
        0.5,
        0
      ],
      "Size": [
        6,
        1,
        6
      ],
      "Transparency": 0.5,
      "Duration": 0
    }
  }
}
}
